pybot_adapter_slack-0.0.2.dist-info/DESCRIPTION.rst
pybot_adapter_slack-0.0.2.dist-info/METADATA
pybot_adapter_slack-0.0.2.dist-info/RECORD
pybot_adapter_slack-0.0.2.dist-info/WHEEL
pybot_adapter_slack-0.0.2.dist-info/metadata.json
pybot_adapter_slack-0.0.2.dist-info/top_level.txt
pybot_slack/__init__.py
pybot_slack/adapter.py
