Metadata-Version: 2.0
Name: pybot-adapter-slack
Version: 0.0.2
Summary: Slack adapter for pybot
Home-page: https://github.com/jcomo/pybot-adapter-slack
Author: Jonathan Como
Author-email: jonathan.como@gmail.com
License: UNKNOWN
Keywords: python chat bot framework automation slack
Platform: UNKNOWN
Classifier: Programming Language :: Python :: 2
Classifier: Programming Language :: Python :: 2.6
Classifier: Programming Language :: Python :: 2.7
Classifier: Programming Language :: Python :: 3.3
Classifier: Programming Language :: Python :: 3.4
Requires-Dist: slackclient
